xmpy/__init__.py
xmpy/包_事件引擎/__init__.py
xmpy/包_事件引擎/模块_引擎.py
xmpy/包_交易核心/__init__.py
xmpy/包_交易核心/模块_主引擎.py
xmpy/包_交易核心/模块_事件类型.py
xmpy/包_交易核心/模块_优化.py
xmpy/包_交易核心/模块_基础数据库.py
xmpy/包_交易核心/模块_对象.py
xmpy/包_交易核心/模块_工具.py
xmpy/包_交易核心/模块_常数.py
xmpy/包_交易核心/模块_应用.py
xmpy/包_交易核心/模块_数据服务.py
xmpy/包_交易核心/模块_网关.py
xmpy/包_交易核心/模块_设置.py
xmpy/包_交易核心/模块_转换器.py
xmpy/包_交易核心/包_国际化/__init__.py
xmpy-1.0.7.dist-info/METADATA
xmpy-1.0.7.dist-info/WHEEL
xmpy-1.0.7.dist-info/licenses/LICENSE
xmpy-1.0.7.dist-info/RECORD
