Metadata-Version: 2.4
Name: xmpy
Version: 1.0.7
Summary: 专为中文母语开发者打造的量化交易研发框架。
Project-URL: Homepage, https://github.com/InkAbyss/xmpy
Project-URL: Issues, https://github.com/InkAbyss/xmpy/issues
Author-email: bhzy <2024305928@qq.com>
License: MIT
License-File: LICENSE
Keywords: algotrading,investment,quant,quantitative,trading
Classifier: Development Status :: 5 - Production/Stable
Classifier: License :: OSI Approved :: MIT License
Classifier: Natural Language :: Chinese (Simplified)
Classifier: Operating System :: MacOS
Classifier: Operating System :: Microsoft :: Windows
Classifier: Operating System :: POSIX :: Linux
Classifier: Programming Language :: Python :: 3
Classifier: Programming Language :: Python :: 3.10
Classifier: Programming Language :: Python :: 3.11
Classifier: Programming Language :: Python :: 3.12
Classifier: Programming Language :: Python :: 3.13
Classifier: Programming Language :: Python :: Implementation :: CPython
Classifier: Topic :: Office/Business :: Financial :: Investment
Classifier: Typing :: Typed
Requires-Python: >=3.10
Requires-Dist: bs4>=0.0.2
Requires-Dist: deap>=1.4.3
Requires-Dist: numpy>=2.2.3
Requires-Dist: pandas>=2.2.2
Requires-Dist: plotly>=6.2.0
Requires-Dist: requests>=2.32.5
Requires-Dist: ta-lib>=0.6.0
Requires-Dist: tqdm>=4.67.1
Requires-Dist: tzlocal>=5.3
Requires-Dist: xmpy-ctastrategy>=1.0.0
Requires-Dist: xmpy-ctp>=1.0.0
Requires-Dist: xmpy-datarecorder>=1.0.0
Requires-Dist: xmpy-sqlite>=1.0.0
